setup.py
deepdist/__init__.py
deepdist/deepdist.py
deepdist/rwlock.py
deepdist.egg-info/PKG-INFO
deepdist.egg-info/SOURCES.txt
deepdist.egg-info/dependency_links.txt
deepdist.egg-info/not-zip-safe
deepdist.egg-info/top_level.txt