Metadata-Version: 1.0
Name: deepdist
Version: 0.1
Summary: Lighting-Fast Deep Learning on Spark
Home-page: http://deepdist.com
Author: Dirk Neumann
Author-email: dirk@caltech.edu
License: UNKNOWN
Platform: UNKNOWN
